{
	"GaiaDR2 126802":{
		"schema":"https://github.com/astrocatalogs/faststars/blob/4818341/SCHEMA.md",
		"name":"GaiaDR2 126802",
		"sources":[
			{
				"name":"2018arXiv180410607M",
				"bibcode":"2018arXiv180410607M",
				"reference":"Marchetti, Rossi, & Brown (2018)",
				"alias":"1"
			},
			{
				"name":"2016A&A...595A...2G",
				"bibcode":"2016A&A...595A...2G",
				"reference":"Gaia Collaboration et al. (2016)",
				"alias":"2"
			},
			{
				"name":"2015ApJS..219...12A",
				"bibcode":"2015ApJS..219...12A",
				"reference":"Alam et al. (2015)",
				"alias":"3"
			},
			{
				"name":"1998ApJ...500..525S",
				"bibcode":"1998ApJ...500..525S",
				"reference":"Schlegel, Finkbeiner, & Davis (1998)",
				"alias":"4"
			},
			{
				"name":"The Open Supernova Catalog",
				"bibcode":"2017ApJ...835...64G",
				"reference":"Guillochon et al. (2017)",
				"secondary":true,
				"url":"https://sne.space",
				"alias":"5"
			}
		],
		"alias":[
			{
				"value":"GaiaDR2 126802",
				"source":"1"
			},
			{
				"value":"GaiaDR2 1268023196461923712",
				"source":"1"
			}
		],
		"boundprobability":[
			{
				"value":"0.631396",
				"derived":true,
				"e_lower_value":"0.0019734746314286067",
				"e_upper_value":"0.001970547220410457",
				"source":"5"
			}
		],
		"dec":[
			{
				"value":"+26:14:46.7527",
				"u_value":"degrees",
				"source":"1"
			},
			{
				"value":"+26:14:46.7527",
				"correlations":[
					{
						"kind":"Pearson",
						"quantity":"parallax",
						"value":"0.0373"
					},
					{
						"kind":"Pearson",
						"quantity":"propermotionra",
						"value":"-0.1295"
					},
					{
						"kind":"Pearson",
						"quantity":"propermotiondec",
						"value":"0.2059"
					},
					{
						"kind":"Pearson",
						"quantity":"ra",
						"value":"-0.0601"
					}
				],
				"e_value":"0.0171",
				"u_value":"mas",
				"source":"2"
			}
		],
		"discoverdate":[
			{
				"value":"2018",
				"source":"1"
			}
		],
		"discoverer":[
			{
				"value":"T. Marchetti, E. M. Rossi, A. G. A. Brown",
				"source":"1"
			}
		],
		"ebv":[
			{
				"value":"0.0433138",
				"derived":true,
				"upperlimit":true,
				"source":"4"
			}
		],
		"lumdist":[
			{
				"value":"4.50921",
				"derived":true,
				"e_value":"0.467507",
				"u_value":"kpc",
				"source":"5"
			}
		],
		"maxabsmag":[
			{
				"value":"-15.9194",
				"derived":true,
				"source":"5"
			}
		],
		"maxappmag":[
			{
				"value":"12.35",
				"derived":true,
				"source":"2,5"
			}
		],
		"maxband":[
			{
				"value":"GRP",
				"derived":true,
				"source":"2,5"
			}
		],
		"maxdate":[
			{
				"value":"2015/01/01",
				"derived":true,
				"source":"2,5"
			}
		],
		"parallax":[
			{
				"value":"0.2242",
				"correlations":[
					{
						"kind":"Pearson",
						"quantity":"propermotionra",
						"value":"-0.0593"
					},
					{
						"kind":"Pearson",
						"quantity":"propermotiondec",
						"value":"-0.0127"
					},
					{
						"kind":"Pearson",
						"quantity":"ra",
						"value":"-0.3225"
					},
					{
						"kind":"Pearson",
						"quantity":"dec",
						"value":"0.0373"
					}
				],
				"e_value":"0.0225",
				"u_value":"mas",
				"source":"2"
			}
		],
		"propermotiondec":[
			{
				"value":"-18.877",
				"correlations":[
					{
						"kind":"Pearson",
						"quantity":"ra",
						"value":"-0.1008"
					},
					{
						"kind":"Pearson",
						"quantity":"dec",
						"value":"0.2059"
					},
					{
						"kind":"Pearson",
						"quantity":"parallax",
						"value":"-0.0127"
					},
					{
						"kind":"Pearson",
						"quantity":"propermotionra",
						"value":"0.0115"
					}
				],
				"e_value":"0.041",
				"u_value":"mas/yr",
				"source":"2"
			}
		],
		"propermotionra":[
			{
				"value":"-29.641",
				"correlations":[
					{
						"kind":"Pearson",
						"quantity":"propermotiondec",
						"value":"0.0115"
					},
					{
						"kind":"Pearson",
						"quantity":"ra",
						"value":"0.2577"
					},
					{
						"kind":"Pearson",
						"quantity":"dec",
						"value":"-0.1295"
					},
					{
						"kind":"Pearson",
						"quantity":"parallax",
						"value":"-0.0593"
					}
				],
				"e_value":"0.039",
				"u_value":"mas/yr",
				"source":"2"
			}
		],
		"ra":[
			{
				"value":"15:03:08.0597",
				"u_value":"hours",
				"source":"1"
			},
			{
				"value":"15:03:08.0597",
				"correlations":[
					{
						"kind":"Pearson",
						"quantity":"dec",
						"value":"-0.0601"
					},
					{
						"kind":"Pearson",
						"quantity":"parallax",
						"value":"-0.3225"
					},
					{
						"kind":"Pearson",
						"quantity":"propermotionra",
						"value":"0.2577"
					},
					{
						"kind":"Pearson",
						"quantity":"propermotiondec",
						"value":"-0.1008"
					}
				],
				"e_value":"0.015",
				"u_value":"mas",
				"source":"2"
			}
		],
		"velocity":[
			{
				"value":"-276.84",
				"e_value":"1.64",
				"u_value":"km/s",
				"source":"2"
			},
			{
				"value":"573.526",
				"derived":true,
				"e_value":"22.1137",
				"kind":[
					"galactocentric",
					"escape"
				],
				"u_value":"km/s",
				"source":"5"
			},
			{
				"value":"556.985",
				"derived":true,
				"e_value":"73.6546",
				"kind":[
					"galactocentric",
					"total"
				],
				"u_value":"km/s",
				"source":"5"
			}
		],
		"photometry":[
			{
				"time":"53138",
				"band":"g",
				"e_magnitude":"0.005040564",
				"magnitude":"14.97109",
				"telescope":"SDSS",
				"u_time":"MJD",
				"source":"3"
			},
			{
				"time":"53138",
				"band":"i",
				"e_magnitude":"0.01133252",
				"magnitude":"14.27601",
				"telescope":"SDSS",
				"u_time":"MJD",
				"source":"3"
			},
			{
				"time":"53138",
				"band":"r",
				"e_magnitude":"0.009748447",
				"magnitude":"14.8779",
				"telescope":"SDSS",
				"u_time":"MJD",
				"source":"3"
			},
			{
				"time":"53138",
				"band":"u",
				"e_magnitude":"0.006602458",
				"magnitude":"16.10869",
				"telescope":"SDSS",
				"u_time":"MJD",
				"source":"3"
			},
			{
				"time":"53138",
				"band":"z",
				"e_magnitude":"0.005271805",
				"magnitude":"13.56683",
				"telescope":"SDSS",
				"u_time":"MJD",
				"source":"3"
			},
			{
				"time":"57023",
				"band":"G",
				"e_magnitude":"0.0004",
				"instrument":"Astrometric",
				"magnitude":"12.9966",
				"telescope":"Gaia",
				"u_time":"MJD",
				"source":"2"
			},
			{
				"time":"57023",
				"band":"GBP",
				"e_magnitude":"0.0012",
				"magnitude":"13.4889",
				"telescope":"Gaia",
				"u_time":"MJD",
				"source":"2"
			},
			{
				"time":"57023",
				"band":"GRP",
				"e_magnitude":"0.0009",
				"magnitude":"12.3516",
				"telescope":"Gaia",
				"u_time":"MJD",
				"source":"2"
			}
		]
	}
}