{
	"GaiaDR2 6397497209236655872":{
		"schema":"https://github.com/astrocatalogs/faststars/blob/4818341/SCHEMA.md",
		"name":"GaiaDR2 6397497209236655872",
		"sources":[
			{
				"name":"2018arXiv180410607M",
				"bibcode":"2018arXiv180410607M",
				"reference":"Marchetti, Rossi, & Brown (2018)",
				"alias":"1"
			},
			{
				"name":"2016A&A...595A...2G",
				"bibcode":"2016A&A...595A...2G",
				"reference":"Gaia Collaboration et al. (2016)",
				"alias":"2"
			},
			{
				"name":"1998ApJ...500..525S",
				"bibcode":"1998ApJ...500..525S",
				"reference":"Schlegel, Finkbeiner, & Davis (1998)",
				"alias":"3"
			},
			{
				"name":"The Open Supernova Catalog",
				"bibcode":"2017ApJ...835...64G",
				"reference":"Guillochon et al. (2017)",
				"secondary":true,
				"url":"https://sne.space",
				"alias":"4"
			}
		],
		"alias":[
			{
				"value":"GaiaDR2 6397497209236655872",
				"source":"1"
			}
		],
		"boundprobability":[
			{
				"value":"0.559698",
				"derived":true,
				"e_lower_value":"0.0020298924938270124",
				"e_upper_value":"0.002028562459211014",
				"source":"4"
			}
		],
		"dec":[
			{
				"value":"-68:10:06.9457",
				"u_value":"degrees",
				"source":"1"
			},
			{
				"value":"-68:10:06.9457",
				"correlations":[
					{
						"kind":"Pearson",
						"quantity":"parallax",
						"value":"-0.3437"
					},
					{
						"kind":"Pearson",
						"quantity":"propermotionra",
						"value":"0.0235"
					},
					{
						"kind":"Pearson",
						"quantity":"propermotiondec",
						"value":"-0.0967"
					},
					{
						"kind":"Pearson",
						"quantity":"ra",
						"value":"-0.365"
					}
				],
				"e_value":"0.0141",
				"u_value":"mas",
				"source":"2"
			}
		],
		"discoverdate":[
			{
				"value":"2018",
				"source":"1"
			}
		],
		"discoverer":[
			{
				"value":"T. Marchetti, E. M. Rossi, A. G. A. Brown",
				"source":"1"
			}
		],
		"ebv":[
			{
				"value":"0.0322724",
				"derived":true,
				"upperlimit":true,
				"source":"3"
			}
		],
		"lumdist":[
			{
				"value":"5.83649",
				"derived":true,
				"e_value":"0.558517",
				"u_value":"kpc",
				"source":"4"
			}
		],
		"maxabsmag":[
			{
				"value":"-16.2593",
				"derived":true,
				"source":"4"
			}
		],
		"maxappmag":[
			{
				"value":"12.57",
				"derived":true,
				"source":"2,4"
			}
		],
		"maxband":[
			{
				"value":"GRP",
				"derived":true,
				"source":"2,4"
			}
		],
		"maxdate":[
			{
				"value":"2015/01/01",
				"derived":true,
				"source":"2,4"
			}
		],
		"parallax":[
			{
				"value":"0.1727",
				"correlations":[
					{
						"kind":"Pearson",
						"quantity":"propermotionra",
						"value":"-0.0843"
					},
					{
						"kind":"Pearson",
						"quantity":"propermotiondec",
						"value":"-0.0891"
					},
					{
						"kind":"Pearson",
						"quantity":"ra",
						"value":"0.3747"
					},
					{
						"kind":"Pearson",
						"quantity":"dec",
						"value":"-0.3437"
					}
				],
				"e_value":"0.0166",
				"u_value":"mas",
				"source":"2"
			}
		],
		"propermotiondec":[
			{
				"value":"-6.567",
				"correlations":[
					{
						"kind":"Pearson",
						"quantity":"ra",
						"value":"-0.039"
					},
					{
						"kind":"Pearson",
						"quantity":"dec",
						"value":"-0.0967"
					},
					{
						"kind":"Pearson",
						"quantity":"parallax",
						"value":"-0.0891"
					},
					{
						"kind":"Pearson",
						"quantity":"propermotionra",
						"value":"-0.2696"
					}
				],
				"e_value":"0.026",
				"u_value":"mas/yr",
				"source":"2"
			}
		],
		"propermotionra":[
			{
				"value":"-18.709",
				"correlations":[
					{
						"kind":"Pearson",
						"quantity":"propermotiondec",
						"value":"-0.2696"
					},
					{
						"kind":"Pearson",
						"quantity":"ra",
						"value":"0.0383"
					},
					{
						"kind":"Pearson",
						"quantity":"dec",
						"value":"0.0235"
					},
					{
						"kind":"Pearson",
						"quantity":"parallax",
						"value":"-0.0843"
					}
				],
				"e_value":"0.022",
				"u_value":"mas/yr",
				"source":"2"
			}
		],
		"ra":[
			{
				"value":"22:12:27.2198",
				"u_value":"hours",
				"source":"1"
			},
			{
				"value":"22:12:27.2198",
				"correlations":[
					{
						"kind":"Pearson",
						"quantity":"dec",
						"value":"-0.365"
					},
					{
						"kind":"Pearson",
						"quantity":"parallax",
						"value":"0.3747"
					},
					{
						"kind":"Pearson",
						"quantity":"propermotionra",
						"value":"0.0383"
					},
					{
						"kind":"Pearson",
						"quantity":"propermotiondec",
						"value":"-0.039"
					}
				],
				"e_value":"0.0115",
				"u_value":"mas",
				"source":"2"
			}
		],
		"velocity":[
			{
				"value":"-8.16",
				"e_value":"3.61",
				"u_value":"km/s",
				"source":"2"
			},
			{
				"value":"591.941",
				"derived":true,
				"e_value":"22.8591",
				"kind":[
					"galactocentric",
					"escape"
				],
				"u_value":"km/s",
				"source":"4"
			},
			{
				"value":"588.127",
				"derived":true,
				"e_value":"47.5207",
				"kind":[
					"galactocentric",
					"total"
				],
				"u_value":"km/s",
				"source":"4"
			}
		],
		"photometry":[
			{
				"time":"57023",
				"band":"G",
				"e_magnitude":"0.0003",
				"instrument":"Astrometric",
				"magnitude":"13.2053",
				"telescope":"Gaia",
				"u_time":"MJD",
				"source":"2"
			},
			{
				"time":"57023",
				"band":"GBP",
				"e_magnitude":"0.0012",
				"magnitude":"13.6778",
				"telescope":"Gaia",
				"u_time":"MJD",
				"source":"2"
			},
			{
				"time":"57023",
				"band":"GRP",
				"e_magnitude":"0.0013",
				"magnitude":"12.5726",
				"telescope":"Gaia",
				"u_time":"MJD",
				"source":"2"
			}
		]
	}
}