{
	"HVS14":{
		"schema":"https://github.com/astrocatalogs/faststars/blob/4818341/SCHEMA.md",
		"name":"HVS14",
		"sources":[
			{
				"name":"2018arXiv180103555G",
				"bibcode":"2018arXiv180103555G",
				"reference":"Green et al. (2018)",
				"alias":"1"
			},
			{
				"name":"2016A&A...595A...2G",
				"bibcode":"2016A&A...595A...2G",
				"reference":"Gaia Collaboration et al. (2016)",
				"alias":"2"
			},
			{
				"name":"2015ApJS..219...12A",
				"bibcode":"2015ApJS..219...12A",
				"reference":"Alam et al. (2015)",
				"alias":"3"
			},
			{
				"name":"2014ApJ...787...89B",
				"bibcode":"2014ApJ...787...89B",
				"reference":"Brown, Geller, & Kenyon (2014)",
				"alias":"4"
			},
			{
				"name":"2012ApJ...751...55B",
				"bibcode":"2012ApJ...751...55B",
				"reference":"Brown, Geller, & Kenyon (2012)",
				"alias":"5"
			},
			{
				"name":"2009ApJ...690.1639B",
				"bibcode":"2009ApJ...690.1639B",
				"reference":"Brown, Geller, & Kenyon (2009)",
				"alias":"6"
			},
			{
				"name":"The Open Supernova Catalog",
				"bibcode":"2017ApJ...835...64G",
				"reference":"Guillochon et al. (2017)",
				"secondary":true,
				"url":"https://sne.space",
				"alias":"7"
			}
		],
		"alias":[
			{
				"value":"HVS14",
				"source":"4,5,6"
			},
			{
				"value":"SDSSJ104401.75+061139.02",
				"source":"4,5"
			},
			{
				"value":"SDSSJ104401.75+061139.0",
				"source":"6"
			},
			{
				"value":"Gaia DR2 3859275333773935488",
				"source":"2"
			}
		],
		"boundprobability":[
			{
				"value":"0.0341155",
				"derived":true,
				"e_lower_value":"0.00073678816256",
				"e_upper_value":"0.000747167020562",
				"upperlimit":true,
				"source":"7"
			}
		],
		"dec":[
			{
				"value":"+06:11:39.02",
				"u_value":"degrees",
				"source":"4,5"
			},
			{
				"value":"+06:11:39",
				"u_value":"degrees",
				"source":"6"
			},
			{
				"value":"+06:11:39.035",
				"correlations":[
					{
						"kind":"Pearson",
						"quantity":"ra",
						"value":"-0.9176"
					}
				],
				"e_value":"2.68026",
				"u_e_value":"mas",
				"u_value":"degrees",
				"source":"2"
			}
		],
		"discoverdate":[
			{
				"value":"2012",
				"source":"5"
			},
			{
				"value":"2009",
				"source":"6"
			}
		],
		"discoverer":[
			{
				"value":"Warren R. Brown, Margaret J. Geller, Scott J. Kenyon",
				"source":"5,6"
			}
		],
		"ebv":[
			{
				"value":"0.02865",
				"derived":true,
				"source":"1"
			}
		],
		"lumdist":[
			{
				"value":"105.079",
				"derived":true,
				"e_lower_value":"16.0590196022",
				"e_upper_value":"16.0433466008",
				"u_value":"kpc",
				"source":"4"
			}
		],
		"maxabsmag":[
			{
				"value":"-15.2925",
				"derived":true,
				"source":"4,7"
			}
		],
		"maxappmag":[
			{
				"value":"19.79",
				"derived":true,
				"source":"3,7"
			}
		],
		"maxband":[
			{
				"value":"g",
				"derived":true,
				"source":"3,7"
			}
		],
		"maxdate":[
			{
				"value":"2002/02/13",
				"derived":true,
				"source":"3,7"
			}
		],
		"ra":[
			{
				"value":"10:44:01.75",
				"u_value":"hours",
				"source":"4,5,6"
			},
			{
				"value":"10:44:01.7473",
				"correlations":[
					{
						"kind":"Pearson",
						"quantity":"dec",
						"value":"-0.9176"
					}
				],
				"e_value":"2.56321",
				"u_e_value":"mas",
				"u_value":"hours",
				"source":"2"
			}
		],
		"spectraltype":[
			{
				"value":"B",
				"source":"6"
			}
		],
		"stellarclass":[
			{
				"value":"d",
				"source":"6"
			}
		],
		"velocity":[
			{
				"value":"532",
				"e_value":"13",
				"u_value":"km/s",
				"source":"6"
			},
			{
				"value":"537.3",
				"e_value":"7.2",
				"u_value":"km/s",
				"source":"4"
			},
			{
				"value":"331.57",
				"derived":true,
				"e_value":"38.8831",
				"kind":[
					"galactocentric",
					"escape"
				],
				"u_value":"km/s",
				"source":"7"
			},
			{
				"value":"407.781",
				"derived":true,
				"e_value":"9.1256",
				"kind":[
					"galactocentric",
					"total"
				],
				"lowerlimit":true,
				"u_value":"km/s",
				"source":"7"
			}
		],
		"photometry":[
			{
				"time":"52318",
				"band":"g",
				"e_magnitude":"0.01474424",
				"magnitude":"19.78638",
				"telescope":"SDSS",
				"u_time":"MJD",
				"source":"3"
			},
			{
				"time":"52318",
				"band":"i",
				"e_magnitude":"0.03206833",
				"magnitude":"20.26131",
				"telescope":"SDSS",
				"u_time":"MJD",
				"source":"3"
			},
			{
				"time":"52318",
				"band":"r",
				"e_magnitude":"0.02211396",
				"magnitude":"20.10795",
				"telescope":"SDSS",
				"u_time":"MJD",
				"source":"3"
			},
			{
				"time":"52318",
				"band":"u",
				"e_magnitude":"0.05733593",
				"magnitude":"20.57808",
				"telescope":"SDSS",
				"u_time":"MJD",
				"source":"3"
			},
			{
				"time":"52318",
				"band":"z",
				"e_magnitude":"0.1367891",
				"magnitude":"20.64054",
				"telescope":"SDSS",
				"u_time":"MJD",
				"source":"3"
			},
			{
				"time":"57023",
				"band":"G",
				"e_magnitude":"0.0088",
				"instrument":"Astrometric",
				"magnitude":"20.0144",
				"telescope":"Gaia",
				"u_time":"MJD",
				"source":"2"
			},
			{
				"time":"57023",
				"band":"GBP",
				"e_magnitude":"0.1047",
				"magnitude":"19.9891",
				"telescope":"Gaia",
				"u_time":"MJD",
				"source":"2"
			},
			{
				"time":"57023",
				"band":"GRP",
				"e_magnitude":"0.1409",
				"magnitude":"19.9577",
				"telescope":"Gaia",
				"u_time":"MJD",
				"source":"2"
			}
		]
	}
}