{
	"NHCb":{
		"schema":"https://github.com/astrocatalogs/faststars/blob/4818341/SCHEMA.md",
		"name":"NHCb",
		"sources":[
			{
				"name":"2018arXiv180410121B",
				"bibcode":"2018arXiv180410121B",
				"reference":"Bailer-Jones et al. (2018)",
				"alias":"1"
			},
			{
				"name":"2018arXiv180103555G",
				"bibcode":"2018arXiv180103555G",
				"reference":"Green et al. (2018)",
				"alias":"2"
			},
			{
				"name":"2016A&A...595A...2G",
				"bibcode":"2016A&A...595A...2G",
				"reference":"Gaia Collaboration et al. (2016)",
				"alias":"3"
			},
			{
				"name":"2015ApJS..219...12A",
				"bibcode":"2015ApJS..219...12A",
				"reference":"Alam et al. (2015)",
				"alias":"4"
			},
			{
				"name":"2014EAS....67..255Z",
				"bibcode":"2014EAS....67..255Z",
				"reference":"Zhang, Smith, & Carlin (2014)",
				"alias":"5"
			},
			{
				"name":"The Open Supernova Catalog",
				"bibcode":"2017ApJ...835...64G",
				"reference":"Guillochon et al. (2017)",
				"secondary":true,
				"url":"https://sne.space",
				"alias":"6"
			}
		],
		"alias":[
			{
				"value":"NHCb",
				"source":"5"
			},
			{
				"value":"Gaia DR2 2507508083291363712",
				"source":"3"
			}
		],
		"boundprobability":[
			{
				"value":"0.554098",
				"derived":true,
				"e_lower_value":"0.00203245206928",
				"e_upper_value":"0.00203124679497",
				"source":"6"
			}
		],
		"dec":[
			{
				"value":"-00:18:00.396",
				"u_value":"degrees",
				"source":"5"
			},
			{
				"value":"-00:18:01.6256",
				"correlations":[
					{
						"kind":"Pearson",
						"quantity":"parallax",
						"value":"-0.5393"
					},
					{
						"kind":"Pearson",
						"quantity":"propermotionra",
						"value":"0.1878"
					},
					{
						"kind":"Pearson",
						"quantity":"propermotiondec",
						"value":"0.1549"
					},
					{
						"kind":"Pearson",
						"quantity":"ra",
						"value":"-0.3431"
					}
				],
				"e_u_value":"mas",
				"e_value":"0.221945",
				"u_value":"dms",
				"source":"3"
			}
		],
		"discoverdate":[
			{
				"value":"2014",
				"source":"5"
			}
		],
		"discoverer":[
			{
				"value":"Y. Q. Zhang, M. C. Smith, J. L. Carlin",
				"source":"5"
			}
		],
		"distancepriorlengthscale":[
			{
				"value":"0.338963",
				"u_value":"kpc",
				"source":"1"
			}
		],
		"ebv":[
			{
				"value":"0.0262021",
				"derived":true,
				"source":"2"
			}
		],
		"lumdist":[
			{
				"value":"1.31471",
				"derived":true,
				"e_value":"0.424778",
				"u_value":"kpc",
				"source":"6"
			}
		],
		"maxabsmag":[
			{
				"value":"-8.02383",
				"derived":true,
				"source":"6"
			}
		],
		"maxappmag":[
			{
				"value":"17.57",
				"derived":true,
				"source":"3,6"
			}
		],
		"maxband":[
			{
				"value":"GRP",
				"derived":true,
				"source":"3,6"
			}
		],
		"maxdate":[
			{
				"value":"2015/01/01",
				"derived":true,
				"source":"3,6"
			}
		],
		"parallax":[
			{
				"value":"0.8106",
				"correlations":[
					{
						"kind":"Pearson",
						"quantity":"propermotionra",
						"value":"-0.0445"
					},
					{
						"kind":"Pearson",
						"quantity":"propermotiondec",
						"value":"-0.0147"
					},
					{
						"kind":"Pearson",
						"quantity":"ra",
						"value":"0.5893"
					},
					{
						"kind":"Pearson",
						"quantity":"dec",
						"value":"-0.5393"
					}
				],
				"e_u_value":"mas",
				"e_value":"0.370421",
				"u_value":"mas",
				"source":"3"
			}
		],
		"propermotiondec":[
			{
				"value":"-108.89",
				"e_value":"0.57",
				"u_value":"mas/yr",
				"source":"5"
			},
			{
				"value":"-108.479",
				"correlations":[
					{
						"kind":"Pearson",
						"quantity":"ra",
						"value":"0.1034"
					},
					{
						"kind":"Pearson",
						"quantity":"dec",
						"value":"0.1549"
					},
					{
						"kind":"Pearson",
						"quantity":"parallax",
						"value":"-0.0147"
					},
					{
						"kind":"Pearson",
						"quantity":"propermotionra",
						"value":"0.0908"
					}
				],
				"e_u_value":"mas/yr",
				"e_value":"0.391537",
				"u_value":"mas/yr",
				"source":"3"
			}
		],
		"propermotionra":[
			{
				"value":"27.52",
				"e_value":"0.57",
				"u_value":"mas/yr",
				"source":"5"
			},
			{
				"value":"28.42",
				"correlations":[
					{
						"kind":"Pearson",
						"quantity":"propermotiondec",
						"value":"0.0908"
					},
					{
						"kind":"Pearson",
						"quantity":"ra",
						"value":"-0.2549"
					},
					{
						"kind":"Pearson",
						"quantity":"dec",
						"value":"0.1878"
					},
					{
						"kind":"Pearson",
						"quantity":"parallax",
						"value":"-0.0445"
					}
				],
				"e_u_value":"mas/yr",
				"e_value":"0.570809",
				"u_value":"mas/yr",
				"source":"3"
			}
		],
		"ra":[
			{
				"value":"01:56:45.407",
				"u_value":"hours",
				"source":"5"
			},
			{
				"value":"01:56:45.4287",
				"correlations":[
					{
						"kind":"Pearson",
						"quantity":"dec",
						"value":"-0.3431"
					},
					{
						"kind":"Pearson",
						"quantity":"parallax",
						"value":"0.5893"
					},
					{
						"kind":"Pearson",
						"quantity":"propermotionra",
						"value":"-0.2549"
					},
					{
						"kind":"Pearson",
						"quantity":"propermotiondec",
						"value":"0.1034"
					}
				],
				"e_u_value":"mas",
				"e_value":"0.332257",
				"u_value":"hms",
				"source":"3"
			}
		],
		"spectraltype":[
			{
				"value":"K",
				"source":"5"
			},
			{
				"value":"M",
				"source":"5"
			}
		],
		"stellarclass":[
			{
				"value":"d",
				"source":"5"
			}
		],
		"velocity":[
			{
				"value":"-235.4",
				"e_value":"10",
				"u_value":"km/s",
				"source":"5"
			},
			{
				"value":"522.121",
				"derived":true,
				"e_value":"42.2474",
				"kind":[
					"galactocentric",
					"escape"
				],
				"u_value":"km/s",
				"source":"6"
			},
			{
				"value":"539.559",
				"derived":true,
				"e_value":"205.566",
				"kind":[
					"galactocentric",
					"total"
				],
				"u_value":"km/s",
				"source":"6"
			}
		],
		"photometry":[
			{
				"time":"52963",
				"band":"g",
				"e_magnitude":"0.01206695",
				"magnitude":"19.51843",
				"telescope":"SDSS",
				"u_time":"MJD",
				"source":"4"
			},
			{
				"time":"52963",
				"band":"i",
				"e_magnitude":"0.008026617",
				"magnitude":"17.92701",
				"telescope":"SDSS",
				"u_time":"MJD",
				"source":"4"
			},
			{
				"time":"52963",
				"band":"r",
				"e_magnitude":"0.008258245",
				"magnitude":"18.36314",
				"telescope":"SDSS",
				"u_time":"MJD",
				"source":"4"
			},
			{
				"time":"52963",
				"band":"u",
				"e_magnitude":"0.1286905",
				"magnitude":"21.90438",
				"telescope":"SDSS",
				"u_time":"MJD",
				"source":"4"
			},
			{
				"time":"52963",
				"band":"z",
				"e_magnitude":"0.01519167",
				"magnitude":"17.62716",
				"telescope":"SDSS",
				"u_time":"MJD",
				"source":"4"
			},
			{
				"time":"57023",
				"band":"G",
				"e_magnitude":"0.003",
				"instrument":"Astrometric",
				"magnitude":"18.3769",
				"telescope":"Gaia",
				"u_time":"MJD",
				"source":"3"
			},
			{
				"time":"57023",
				"band":"GBP",
				"e_magnitude":"0.0648",
				"magnitude":"18.9474",
				"telescope":"Gaia",
				"u_time":"MJD",
				"source":"3"
			},
			{
				"time":"57023",
				"band":"GRP",
				"e_magnitude":"0.0218",
				"magnitude":"17.5671",
				"telescope":"Gaia",
				"u_time":"MJD",
				"source":"3"
			}
		]
	}
}