{
	"Pal18":{
		"schema":"https://github.com/astrocatalogs/faststars/blob/4818341/SCHEMA.md",
		"name":"Pal18",
		"sources":[
			{
				"name":"2015A&A...576L..14Z",
				"bibcode":"2015A&A...576L..14Z",
				"reference":"Ziegerer et al. (2015)",
				"alias":"1"
			},
			{
				"name":"2014ApJ...780....7P",
				"bibcode":"2014ApJ...780....7P",
				"reference":"Palladino et al. (2014)",
				"alias":"2"
			},
			{
				"bibcode":"2015ApJS..219...12A",
				"alias":"3"
			},
			{
				"bibcode":"2016A&A...595A...2G",
				"alias":"4"
			},
			{
				"name":"SIMBAD astronomical database",
				"bibcode":"2000A&AS..143....9W",
				"secondary":true,
				"url":"http://simbad.u-strasbg.fr/",
				"alias":"5"
			},
			{
				"bibcode":"2018arXiv180103555G",
				"alias":"6"
			},
			{
				"name":"The Open Supernova Catalog",
				"bibcode":"2017ApJ...835...64G",
				"secondary":true,
				"url":"https://sne.space",
				"alias":"7"
			}
		],
		"alias":[
			{
				"value":"Pal18",
				"source":"1,2"
			},
			{
				"value":"SDSSJ165956.02+392414.9",
				"source":"2,5"
			}
		],
		"boundprobability":[
			{
				"value":"0.999483",
				"derived":true,
				"e_lower_value":"9.803482324644008e-05",
				"e_upper_value":"8.696837835397986e-05",
				"source":"7"
			}
		],
		"dec":[
			{
				"value":"+39:24:14.9",
				"u_value":"degrees",
				"source":"2"
			},
			{
				"value":"+39:24:14.8443",
				"correlations":[
					{
						"kind":"Pearson",
						"quantity":"parallax",
						"value":"-0.0246"
					},
					{
						"kind":"Pearson",
						"quantity":"propermotionra",
						"value":"-0.0453"
					},
					{
						"kind":"Pearson",
						"quantity":"propermotiondec",
						"value":"-0.2252"
					},
					{
						"kind":"Pearson",
						"quantity":"ra",
						"value":"0.1254"
					}
				],
				"e_value":"0.2415",
				"u_value":"mas",
				"source":"4"
			}
		],
		"discoverdate":[
			{
				"value":"2014",
				"source":"2"
			}
		],
		"discoverer":[
			{
				"value":"Lauren E. Palladino, Katharine J. Schlesinger, Kelly Holley-Bockelmann, Carlos Allende Prieto, Timothy C. Beers, Young Sun Lee, Donald P. Schneider",
				"source":"2"
			}
		],
		"ebv":[
			{
				"value":"0.03643",
				"derived":true,
				"source":"6"
			}
		],
		"lumdist":[
			{
				"value":"5.32031",
				"derived":true,
				"e_value":"2.26211",
				"u_value":"kpc",
				"source":"7"
			}
		],
		"parallax":[
			{
				"value":"-0.0162",
				"correlations":[
					{
						"kind":"Pearson",
						"quantity":"propermotionra",
						"value":"-0.1096"
					},
					{
						"kind":"Pearson",
						"quantity":"propermotiondec",
						"value":"0.169"
					},
					{
						"kind":"Pearson",
						"quantity":"ra",
						"value":"-0.3069"
					},
					{
						"kind":"Pearson",
						"quantity":"dec",
						"value":"-0.0246"
					}
				],
				"e_value":"0.2671",
				"u_value":"mas",
				"source":"4"
			}
		],
		"propermotiondec":[
			{
				"value":"-7.334",
				"correlations":[
					{
						"kind":"Pearson",
						"quantity":"ra",
						"value":"-0.0472"
					},
					{
						"kind":"Pearson",
						"quantity":"dec",
						"value":"-0.2252"
					},
					{
						"kind":"Pearson",
						"quantity":"parallax",
						"value":"0.169"
					},
					{
						"kind":"Pearson",
						"quantity":"propermotionra",
						"value":"0.4151"
					}
				],
				"e_value":"0.551",
				"u_value":"mas/yr",
				"source":"4"
			}
		],
		"propermotionra":[
			{
				"value":"-4.223",
				"correlations":[
					{
						"kind":"Pearson",
						"quantity":"propermotiondec",
						"value":"0.4151"
					},
					{
						"kind":"Pearson",
						"quantity":"ra",
						"value":"-0.0242"
					},
					{
						"kind":"Pearson",
						"quantity":"dec",
						"value":"-0.0453"
					},
					{
						"kind":"Pearson",
						"quantity":"parallax",
						"value":"-0.1096"
					}
				],
				"e_value":"0.501",
				"u_value":"mas/yr",
				"source":"4"
			}
		],
		"ra":[
			{
				"value":"16:59:56.02",
				"u_value":"hours",
				"source":"2"
			},
			{
				"value":"16:59:56.0266",
				"correlations":[
					{
						"kind":"Pearson",
						"quantity":"dec",
						"value":"0.1254"
					},
					{
						"kind":"Pearson",
						"quantity":"parallax",
						"value":"-0.3069"
					},
					{
						"kind":"Pearson",
						"quantity":"propermotionra",
						"value":"-0.0242"
					},
					{
						"kind":"Pearson",
						"quantity":"propermotiondec",
						"value":"-0.0472"
					}
				],
				"e_value":"0.2233",
				"u_value":"mas",
				"source":"4"
			}
		],
		"spectraltype":[
			{
				"value":"G",
				"source":"2"
			},
			{
				"value":"K",
				"source":"2"
			}
		],
		"stellarclass":[
			{
				"value":"d",
				"source":"2"
			}
		],
		"velocity":[
			{
				"value":"-205.1",
				"u_value":"km/s",
				"source":"2"
			},
			{
				"value":"560.297",
				"derived":true,
				"e_value":"22.1098",
				"kind":[
					"galactocentric",
					"escape"
				],
				"u_value":"km/s",
				"source":"7"
			},
			{
				"value":"160.089",
				"derived":true,
				"e_value":"67.4208",
				"kind":[
					"galactocentric",
					"total"
				],
				"u_value":"km/s",
				"source":"7"
			}
		],
		"photometry":[
			{
				"time":"53879",
				"band":"u",
				"e_magnitude":"0.09058395",
				"magnitude":"21.15823",
				"telescope":"SDSS",
				"u_time":"MJD",
				"source":"3"
			},
			{
				"time":"53879",
				"band":"g",
				"e_magnitude":"0.01476456",
				"magnitude":"19.8245",
				"telescope":"SDSS",
				"u_time":"MJD",
				"source":"3"
			},
			{
				"time":"53879",
				"band":"r",
				"e_magnitude":"0.01323108",
				"magnitude":"19.28718",
				"telescope":"SDSS",
				"u_time":"MJD",
				"source":"3"
			},
			{
				"time":"53879",
				"band":"i",
				"e_magnitude":"0.01471741",
				"magnitude":"19.0948",
				"telescope":"SDSS",
				"u_time":"MJD",
				"source":"3"
			},
			{
				"time":"53879",
				"band":"z",
				"e_magnitude":"0.04443568",
				"magnitude":"18.95613",
				"telescope":"SDSS",
				"u_time":"MJD",
				"source":"3"
			},
			{
				"time":"57023",
				"band":"G",
				"e_magnitude":"0.0034",
				"instrument":"Astrometric",
				"magnitude":"19.3279",
				"telescope":"Gaia",
				"u_time":"MJD",
				"source":"4"
			},
			{
				"time":"57023",
				"band":"GBP",
				"e_magnitude":"0.0311",
				"magnitude":"19.657",
				"telescope":"Gaia",
				"u_time":"MJD",
				"source":"4"
			},
			{
				"time":"57023",
				"band":"GRP",
				"e_magnitude":"0.0462",
				"magnitude":"18.6266",
				"telescope":"Gaia",
				"u_time":"MJD",
				"source":"4"
			}
		]
	}
}