{
	"SDSSJ081828.07+570922.07":{
		"schema":"https://github.com/astrocatalogs/faststars/blob/4818341/SCHEMA.md",
		"name":"SDSSJ081828.07+570922.07",
		"sources":[
			{
				"name":"2014ApJ...787...89B",
				"bibcode":"2014ApJ...787...89B",
				"reference":"Brown, Geller, & Kenyon (2014)",
				"alias":"1"
			},
			{
				"name":"2012ApJ...751...55B",
				"bibcode":"2012ApJ...751...55B",
				"reference":"Brown, Geller, & Kenyon (2012)",
				"alias":"2"
			}
		],
		"alias":[
			{
				"value":"SDSSJ081828.07+570922.07",
				"source":"1,2"
			}
		],
		"claimedtype":[
			{
				"value":"pBHVS",
				"source":"1,2"
			}
		],
		"dec":[
			{
				"value":"+57:09:17.8353",
				"u_value":"degrees",
				"source":"2"
			},
			{
				"value":"+57:09:22.07",
				"u_value":"degrees",
				"source":"1"
			}
		],
		"host":[
			{
				"value":"Milky Way",
				"derived":true,
				"source":"2"
			}
		],
		"lumdist":[
			{
				"value":"27.1397",
				"u_value":"kpc",
				"source":"2"
			},
			{
				"value":"30.2798",
				"e_lower_value":"4.17470490555",
				"e_upper_value":"4.13273407516",
				"u_value":"kpc",
				"source":"1"
			}
		],
		"ra":[
			{
				"value":"08:18:30.0834",
				"u_value":"hours",
				"source":"2"
			},
			{
				"value":"08:18:28.07",
				"u_value":"hours",
				"source":"1"
			}
		],
		"velocity":[
			{
				"value":"216.1",
				"e_value":"4.4",
				"u_value":"km/s",
				"source":"1"
			}
		]
	}
}