{
	"SDSSJ235103.13+360020.5":{
		"schema":"https://github.com/astrocatalogs/faststars/blob/4818341/SCHEMA.md",
		"name":"SDSSJ235103.13+360020.5",
		"sources":[
			{
				"name":"2016A&A...595A...2G",
				"bibcode":"2016A&A...595A...2G",
				"reference":"Gaia Collaboration et al. (2016)",
				"alias":"1"
			},
			{
				"name":"2015AJ....150...77V",
				"bibcode":"2015AJ....150...77V",
				"reference":"Vickers, Smith, & Grebel (2015)",
				"alias":"2"
			},
			{
				"name":"2015ApJS..219...12A",
				"bibcode":"2015ApJS..219...12A",
				"reference":"Alam et al. (2015)",
				"alias":"3"
			},
			{
				"name":"1998ApJ...500..525S",
				"bibcode":"1998ApJ...500..525S",
				"reference":"Schlegel, Finkbeiner, & Davis (1998)",
				"alias":"4"
			},
			{
				"name":"The Open Supernova Catalog",
				"bibcode":"2017ApJ...835...64G",
				"reference":"Guillochon et al. (2017)",
				"secondary":true,
				"url":"https://sne.space",
				"alias":"5"
			},
			{
				"name":"SIMBAD astronomical database",
				"bibcode":"2000A&AS..143....9W",
				"reference":"Wenger et al. (2000)",
				"secondary":true,
				"url":"http://simbad.u-strasbg.fr/",
				"alias":"6"
			}
		],
		"alias":[
			{
				"value":"SDSSJ235103.13+360020.5",
				"source":"6"
			},
			{
				"value":"SDSSJ235103.13+360020.55",
				"source":"2"
			}
		],
		"boundprobability":[
			{
				"value":"0.999977",
				"derived":true,
				"e_lower_value":"2.2519578492752323e-05",
				"e_upper_value":"1.2987903849959181e-05",
				"upperlimit":true,
				"source":"5"
			}
		],
		"dec":[
			{
				"value":"+36:00:20.55",
				"u_value":"degrees",
				"source":"2"
			},
			{
				"value":"+36:00:20.5369",
				"correlations":[
					{
						"kind":"Pearson",
						"quantity":"parallax",
						"value":"0.1737"
					},
					{
						"kind":"Pearson",
						"quantity":"propermotionra",
						"value":"-0.1059"
					},
					{
						"kind":"Pearson",
						"quantity":"propermotiondec",
						"value":"-0.2091"
					},
					{
						"kind":"Pearson",
						"quantity":"ra",
						"value":"0.2031"
					}
				],
				"e_value":"0.0364",
				"u_value":"mas",
				"source":"1"
			}
		],
		"discoverdate":[
			{
				"value":"2015",
				"source":"2"
			}
		],
		"discoverer":[
			{
				"value":"John J.Vickers, Martin C. Smith, Eva K. Grebel",
				"source":"2"
			}
		],
		"ebv":[
			{
				"value":"0.0859983",
				"derived":true,
				"upperlimit":true,
				"source":"4"
			}
		],
		"lumdist":[
			{
				"value":"2.1812",
				"derived":true,
				"e_value":"0.396453",
				"u_value":"kpc",
				"source":"5"
			}
		],
		"maxabsmag":[
			{
				"value":"-10.9729",
				"derived":true,
				"source":"5"
			}
		],
		"maxappmag":[
			{
				"value":"15.72",
				"derived":true,
				"source":"1,5"
			}
		],
		"maxband":[
			{
				"value":"GRP",
				"derived":true,
				"source":"1,5"
			}
		],
		"maxdate":[
			{
				"value":"2015/01/01",
				"derived":true,
				"source":"1,5"
			}
		],
		"parallax":[
			{
				"value":"0.5038",
				"correlations":[
					{
						"kind":"Pearson",
						"quantity":"propermotionra",
						"value":"-0.371"
					},
					{
						"kind":"Pearson",
						"quantity":"propermotiondec",
						"value":"-0.089"
					},
					{
						"kind":"Pearson",
						"quantity":"ra",
						"value":"0.4941"
					},
					{
						"kind":"Pearson",
						"quantity":"dec",
						"value":"0.1737"
					}
				],
				"e_value":"0.071",
				"u_value":"mas",
				"source":"1"
			}
		],
		"propermotiondec":[
			{
				"value":"-3.043",
				"correlations":[
					{
						"kind":"Pearson",
						"quantity":"ra",
						"value":"-0.0661"
					},
					{
						"kind":"Pearson",
						"quantity":"dec",
						"value":"-0.2091"
					},
					{
						"kind":"Pearson",
						"quantity":"parallax",
						"value":"-0.089"
					},
					{
						"kind":"Pearson",
						"quantity":"propermotionra",
						"value":"0.0228"
					}
				],
				"e_value":"0.058",
				"u_value":"mas/yr",
				"source":"1"
			}
		],
		"propermotionra":[
			{
				"value":"-3.241",
				"correlations":[
					{
						"kind":"Pearson",
						"quantity":"propermotiondec",
						"value":"0.0228"
					},
					{
						"kind":"Pearson",
						"quantity":"ra",
						"value":"-0.4406"
					},
					{
						"kind":"Pearson",
						"quantity":"dec",
						"value":"-0.1059"
					},
					{
						"kind":"Pearson",
						"quantity":"parallax",
						"value":"-0.371"
					}
				],
				"e_value":"0.08",
				"u_value":"mas/yr",
				"source":"1"
			}
		],
		"ra":[
			{
				"value":"23:51:03.13",
				"u_value":"hours",
				"source":"2"
			},
			{
				"value":"23:51:03.1261",
				"correlations":[
					{
						"kind":"Pearson",
						"quantity":"dec",
						"value":"0.2031"
					},
					{
						"kind":"Pearson",
						"quantity":"parallax",
						"value":"0.4941"
					},
					{
						"kind":"Pearson",
						"quantity":"propermotionra",
						"value":"-0.4406"
					},
					{
						"kind":"Pearson",
						"quantity":"propermotiondec",
						"value":"-0.0661"
					}
				],
				"e_value":"0.0475",
				"u_value":"mas",
				"source":"1"
			}
		],
		"spectraltype":[
			{
				"value":"F",
				"source":"2"
			},
			{
				"value":"G",
				"source":"2"
			},
			{
				"value":"K",
				"source":"2"
			},
			{
				"value":"M",
				"source":"2"
			}
		],
		"stellarclass":[
			{
				"value":"d",
				"source":"2"
			}
		],
		"velocity":[
			{
				"value":"541.891",
				"derived":true,
				"e_value":"20.6883",
				"kind":[
					"galactocentric",
					"escape"
				],
				"u_value":"km/s",
				"source":"5"
			},
			{
				"value":"158.578",
				"derived":true,
				"e_value":"6.42777",
				"kind":[
					"galactocentric",
					"total"
				],
				"lowerlimit":true,
				"u_value":"km/s",
				"source":"5"
			}
		],
		"photometry":[
			{
				"time":"52911",
				"band":"g",
				"e_magnitude":"0.004022736",
				"magnitude":"16.84352",
				"telescope":"SDSS",
				"u_time":"MJD",
				"source":"3"
			},
			{
				"time":"52911",
				"band":"i",
				"e_magnitude":"0.003989516",
				"magnitude":"16.04601",
				"telescope":"SDSS",
				"u_time":"MJD",
				"source":"3"
			},
			{
				"time":"52911",
				"band":"r",
				"e_magnitude":"0.003637399",
				"magnitude":"16.25551",
				"telescope":"SDSS",
				"u_time":"MJD",
				"source":"3"
			},
			{
				"time":"52911",
				"band":"u",
				"e_magnitude":"0.01702381",
				"magnitude":"18.46519",
				"telescope":"SDSS",
				"u_time":"MJD",
				"source":"3"
			},
			{
				"time":"52911",
				"band":"z",
				"e_magnitude":"0.006614962",
				"magnitude":"15.94482",
				"telescope":"SDSS",
				"u_time":"MJD",
				"source":"3"
			},
			{
				"time":"57023",
				"band":"G",
				"e_magnitude":"0.0007",
				"instrument":"Astrometric",
				"magnitude":"16.2923",
				"telescope":"Gaia",
				"u_time":"MJD",
				"source":"1"
			},
			{
				"time":"57023",
				"band":"GBP",
				"e_magnitude":"0.0058",
				"magnitude":"16.7343",
				"telescope":"Gaia",
				"u_time":"MJD",
				"source":"1"
			},
			{
				"time":"57023",
				"band":"GRP",
				"e_magnitude":"0.0047",
				"magnitude":"15.7156",
				"telescope":"Gaia",
				"u_time":"MJD",
				"source":"1"
			}
		]
	}
}