{
	"SDSSJ074722.67+283724.7":{
		"schema":"https://github.com/astrocatalogs/faststars/blob/4818341/SCHEMA.md",
		"name":"SDSSJ074722.67+283724.7",
		"sources":[
			{
				"name":"2016A&A...595A...2G",
				"bibcode":"2016A&A...595A...2G",
				"reference":"Gaia Collaboration et al. (2016)",
				"alias":"1"
			},
			{
				"name":"2015AJ....150...77V",
				"bibcode":"2015AJ....150...77V",
				"reference":"Vickers, Smith, & Grebel (2015)",
				"alias":"2"
			},
			{
				"name":"2015ApJS..219...12A",
				"bibcode":"2015ApJS..219...12A",
				"reference":"Alam et al. (2015)",
				"alias":"3"
			},
			{
				"name":"1998ApJ...500..525S",
				"bibcode":"1998ApJ...500..525S",
				"reference":"Schlegel, Finkbeiner, & Davis (1998)",
				"alias":"4"
			},
			{
				"name":"The Open Supernova Catalog",
				"bibcode":"2017ApJ...835...64G",
				"reference":"Guillochon et al. (2017)",
				"secondary":true,
				"url":"https://sne.space",
				"alias":"5"
			},
			{
				"name":"SIMBAD astronomical database",
				"bibcode":"2000A&AS..143....9W",
				"reference":"Wenger et al. (2000)",
				"secondary":true,
				"url":"http://simbad.u-strasbg.fr/",
				"alias":"6"
			}
		],
		"alias":[
			{
				"value":"SDSSJ074722.67+283724.7",
				"source":"6"
			},
			{
				"value":"SDSSJ074722.67+283724.79",
				"source":"2"
			},
			{
				"value":"Gaia DR2 875761664359837952",
				"source":"1"
			}
		],
		"boundprobability":[
			{
				"value":"0.999977",
				"derived":true,
				"e_lower_value":"2.2519578492752323e-05",
				"e_upper_value":"1.2987903849959181e-05",
				"upperlimit":true,
				"source":"5"
			}
		],
		"dec":[
			{
				"value":"+28:37:24.79",
				"u_value":"degrees",
				"source":"2"
			},
			{
				"value":"+28:37:24.7261",
				"correlations":[
					{
						"kind":"Pearson",
						"quantity":"parallax",
						"value":"-0.054"
					},
					{
						"kind":"Pearson",
						"quantity":"propermotionra",
						"value":"-0.1042"
					},
					{
						"kind":"Pearson",
						"quantity":"propermotiondec",
						"value":"0.6053"
					},
					{
						"kind":"Pearson",
						"quantity":"ra",
						"value":"0.0765"
					}
				],
				"e_u_value":"mas",
				"e_value":"0.1563",
				"u_value":"dms",
				"source":"1"
			}
		],
		"discoverdate":[
			{
				"value":"2015",
				"source":"2"
			}
		],
		"discoverer":[
			{
				"value":"John J.Vickers, Martin C. Smith, Eva K. Grebel",
				"source":"2"
			}
		],
		"ebv":[
			{
				"value":"0.0339714",
				"derived":true,
				"upperlimit":true,
				"source":"4"
			}
		],
		"lumdist":[
			{
				"value":"4.97436",
				"derived":true,
				"e_value":"2.50407",
				"u_value":"kpc",
				"source":"5"
			}
		],
		"maxabsmag":[
			{
				"value":"-10.2825",
				"derived":true,
				"source":"5"
			}
		],
		"maxappmag":[
			{
				"value":"18.2",
				"derived":true,
				"source":"1,5"
			}
		],
		"maxband":[
			{
				"value":"GRP",
				"derived":true,
				"source":"1,5"
			}
		],
		"maxdate":[
			{
				"value":"2015/01/01",
				"derived":true,
				"source":"1,5"
			}
		],
		"parallax":[
			{
				"value":"0.0269",
				"correlations":[
					{
						"kind":"Pearson",
						"quantity":"propermotionra",
						"value":"0.5172"
					},
					{
						"kind":"Pearson",
						"quantity":"propermotiondec",
						"value":"0.0147"
					},
					{
						"kind":"Pearson",
						"quantity":"ra",
						"value":"-0.5087"
					},
					{
						"kind":"Pearson",
						"quantity":"dec",
						"value":"-0.054"
					}
				],
				"e_u_value":"mas",
				"e_value":"0.3451",
				"u_value":"mas",
				"source":"1"
			}
		],
		"propermotiondec":[
			{
				"value":"-1.456",
				"correlations":[
					{
						"kind":"Pearson",
						"quantity":"ra",
						"value":"-0.0454"
					},
					{
						"kind":"Pearson",
						"quantity":"dec",
						"value":"0.6053"
					},
					{
						"kind":"Pearson",
						"quantity":"parallax",
						"value":"0.0147"
					},
					{
						"kind":"Pearson",
						"quantity":"propermotionra",
						"value":"-0.0069"
					}
				],
				"e_u_value":"mas/yr",
				"e_value":"0.294",
				"u_value":"mas/yr",
				"source":"1"
			}
		],
		"propermotionra":[
			{
				"value":"-1.384",
				"correlations":[
					{
						"kind":"Pearson",
						"quantity":"propermotiondec",
						"value":"-0.0069"
					},
					{
						"kind":"Pearson",
						"quantity":"ra",
						"value":"-0.3301"
					},
					{
						"kind":"Pearson",
						"quantity":"dec",
						"value":"-0.1042"
					},
					{
						"kind":"Pearson",
						"quantity":"parallax",
						"value":"0.5172"
					}
				],
				"e_u_value":"mas/yr",
				"e_value":"0.536",
				"u_value":"mas/yr",
				"source":"1"
			}
		],
		"ra":[
			{
				"value":"07:47:22.67",
				"u_value":"hours",
				"source":"2"
			},
			{
				"value":"07:47:22.6669",
				"correlations":[
					{
						"kind":"Pearson",
						"quantity":"dec",
						"value":"0.0765"
					},
					{
						"kind":"Pearson",
						"quantity":"parallax",
						"value":"-0.5087"
					},
					{
						"kind":"Pearson",
						"quantity":"propermotionra",
						"value":"-0.3301"
					},
					{
						"kind":"Pearson",
						"quantity":"propermotiondec",
						"value":"-0.0454"
					}
				],
				"e_u_value":"mas",
				"e_value":"0.2967",
				"u_value":"hms",
				"source":"1"
			}
		],
		"spectraltype":[
			{
				"value":"F",
				"source":"2"
			},
			{
				"value":"G",
				"source":"2"
			},
			{
				"value":"K",
				"source":"2"
			},
			{
				"value":"M",
				"source":"2"
			}
		],
		"stellarclass":[
			{
				"value":"d",
				"source":"2"
			}
		],
		"velocity":[
			{
				"value":"509.514",
				"derived":true,
				"e_value":"25.472",
				"kind":[
					"galactocentric",
					"escape"
				],
				"u_value":"km/s",
				"source":"5"
			},
			{
				"value":"222.773",
				"derived":true,
				"e_value":"15.2235",
				"kind":[
					"galactocentric",
					"total"
				],
				"lowerlimit":true,
				"u_value":"km/s",
				"source":"5"
			}
		],
		"photometry":[
			{
				"time":"52261",
				"band":"g",
				"e_magnitude":"0.01304283",
				"magnitude":"19.4392",
				"telescope":"SDSS",
				"u_time":"MJD",
				"source":"3"
			},
			{
				"time":"52261",
				"band":"i",
				"e_magnitude":"0.01149362",
				"magnitude":"18.53919",
				"telescope":"SDSS",
				"u_time":"MJD",
				"source":"3"
			},
			{
				"time":"52261",
				"band":"r",
				"e_magnitude":"0.01014708",
				"magnitude":"18.75532",
				"telescope":"SDSS",
				"u_time":"MJD",
				"source":"3"
			},
			{
				"time":"52261",
				"band":"u",
				"e_magnitude":"0.1239912",
				"magnitude":"21.47996",
				"telescope":"SDSS",
				"u_time":"MJD",
				"source":"3"
			},
			{
				"time":"52261",
				"band":"z",
				"e_magnitude":"0.03438593",
				"magnitude":"18.47125",
				"telescope":"SDSS",
				"u_time":"MJD",
				"source":"3"
			},
			{
				"time":"57023",
				"band":"G",
				"e_magnitude":"0.0026",
				"instrument":"Astrometric",
				"magnitude":"18.826",
				"telescope":"Gaia",
				"u_time":"MJD",
				"source":"1"
			},
			{
				"time":"57023",
				"band":"GBP",
				"e_magnitude":"0.0423",
				"magnitude":"19.2052",
				"telescope":"Gaia",
				"u_time":"MJD",
				"source":"1"
			},
			{
				"time":"57023",
				"band":"GRP",
				"e_magnitude":"0.0302",
				"magnitude":"18.1986",
				"telescope":"Gaia",
				"u_time":"MJD",
				"source":"1"
			}
		]
	}
}